asterisk_wxalert/__init__.py
asterisk_wxalert/wxalert.py
asterisk_wxalert-0.0.1.dist-info/METADATA
asterisk_wxalert-0.0.1.dist-info/WHEEL
asterisk_wxalert-0.0.1.dist-info/entry_points.txt
asterisk_wxalert-0.0.1.dist-info/top_level.txt
asterisk_wxalert-0.0.1.dist-info/RECORD
